vcosmos_mcp_server/__init__.py
vcosmos_mcp_server/server.py
vcosmos_mcp_server-0.1.8.dist-info/METADATA
vcosmos_mcp_server-0.1.8.dist-info/WHEEL
vcosmos_mcp_server-0.1.8.dist-info/entry_points.txt
vcosmos_mcp_server-0.1.8.dist-info/licenses/LICENSE
vcosmos_mcp_server-0.1.8.dist-info/RECORD
