Metadata-Version: 2.4
Name: vcosmos-mcp-server
Version: 0.1.8
Summary: A Model Context Protocol (MCP) server for querying vCosmos Test Logic API - UUTs and Tasks
Project-URL: Homepage, https://github.com/yourusername/vcosmos-mcp-server
Project-URL: Repository, https://github.com/yourusername/vcosmos-mcp-server
Project-URL: Documentation, https://github.com/yourusername/vcosmos-mcp-server#readme
Project-URL: Bug Tracker, https://github.com/yourusername/vcosmos-mcp-server/issues
Author-email: Iverson Lu <iverson.lu@hp.com>
Maintainer-email: Iverson Lu <iverson.lu@hp.com>
License: MIT
License-File: LICENSE
Keywords: api,automation,hp,mcp,model-context-protocol,test,vcosmos
Classifier: Development Status :: 4 - Beta
Classifier: Intended Audience :: Developers
Classifier: License :: OSI Approved :: MIT License
Classifier: Programming Language :: Python :: 3
Classifier: Programming Language :: Python :: 3.8
Classifier: Programming Language :: Python :: 3.9
Classifier: Programming Language :: Python :: 3.10
Classifier: Programming Language :: Python :: 3.11
Classifier: Programming Language :: Python :: 3.12
Classifier: Programming Language :: Python :: 3.13
Classifier: Topic :: Internet :: WWW/HTTP :: Dynamic Content
Classifier: Topic :: Software Development :: Libraries :: Python Modules
Requires-Python: >=3.10
Requires-Dist: mcp>=1.13.1
